retrack/__init__.py
retrack/engine/__init__.py
retrack/engine/base.py
retrack/engine/constructor.py
retrack/engine/executor.py
retrack/engine/request_manager.py
retrack/engine/rule.py
retrack/engine/schemas.py
retrack/nodes/__init__.py
retrack/nodes/base.py
retrack/nodes/check.py
retrack/nodes/connectors.py
retrack/nodes/constants.py
retrack/nodes/contains.py
retrack/nodes/datetime.py
retrack/nodes/dynamic/__init__.py
retrack/nodes/dynamic/base.py
retrack/nodes/dynamic/conditional_connector.py
retrack/nodes/dynamic/csv_table.py
retrack/nodes/dynamic/flow.py
retrack/nodes/dynamic/glm.py
retrack/nodes/endswith.py
retrack/nodes/endswithany.py
retrack/nodes/getchar.py
retrack/nodes/inputs.py
retrack/nodes/logic.py
retrack/nodes/lowercase.py
retrack/nodes/match.py
retrack/nodes/math.py
retrack/nodes/outputs.py
retrack/nodes/start.py
retrack/nodes/startswith.py
retrack/nodes/startswithany.py
retrack/nodes/substring.py
retrack/utils/__init__.py
retrack/utils/component_registry.py
retrack/utils/constants.py
retrack/utils/exceptions.py
retrack/utils/graph.py
retrack/utils/registry.py
retrack/utils/transformers.py
retrack/validators/__init__.py
retrack/validators/base.py
retrack/validators/check_is_dag.py
retrack/validators/node_exists.py
retrack/validators/node_validator.py
retrack-3.4.0.dist-info/LICENSE
retrack-3.4.0.dist-info/METADATA
retrack-3.4.0.dist-info/WHEEL
retrack-3.4.0.dist-info/RECORD
