Metadata-Version: 2.1
Name: retrack
Version: 3.4.0
Summary: A business rules engine
Home-page: https://github.com/pier-digital/retrack
License: MIT
Keywords: rules,models,business,node,graph
Author: Gabriel Guarisa
Author-email: gabriel.guarisa@pier.digital
Requires-Python: >=3.9,<4.0.0
Classifier: License :: OSI Approved :: MIT License
Classifier: Programming Language :: Python :: 3
Classifier: Programming Language :: Python :: 3.9
Classifier: Programming Language :: Python :: 3.10
Classifier: Programming Language :: Python :: 3.11
Requires-Dist: networkx (>=3,<4)
Requires-Dist: numpy (>=1.19.5,<2)
Requires-Dist: pandas (>=2,<3)
Requires-Dist: pandera (>=0.20,<0.21)
Requires-Dist: pydantic (>=2,<3)
Project-URL: Repository, https://github.com/pier-digital/retrack
